quackmyip/__init__.py
quackmyip/quackmyip.py
quackmyip-0.2.2.dist-info/LICENSE
quackmyip-0.2.2.dist-info/METADATA
quackmyip-0.2.2.dist-info/WHEEL
quackmyip-0.2.2.dist-info/entry_points.txt
quackmyip-0.2.2.dist-info/top_level.txt
quackmyip-0.2.2.dist-info/RECORD
