Metadata-Version: 2.1
Name: quackmyip
Version: 0.2.2
Summary: Updates your IP address for your Duck DNS domain
Home-page: https://github.com/tuxedoar/quackmyip
Author: tuxedoar
Author-email: tuxedoar@gmail.com
License: UNKNOWN
Platform: UNKNOWN
Classifier: Programming Language :: Python :: 3
Classifier: License :: OSI Approved :: GNU General Public License v3 (GPLv3)
Classifier: Operating System :: OS Independent
Requires-Dist: urllib3
Requires-Dist: requests
